rp_tagger/__init__.py
rp_tagger/api.py
rp_tagger/db.py
rp_tagger/log.py
rp_tagger/manage.py
rp_tagger/server.py
rp_tagger/conf/__init__.py
rp_tagger/conf/_base.py
rp_tagger/conf/dev.py
rp_tagger/conf/pro.py
rp_tagger/static/__debug__/__0adaa6d28a61b9ab8f6d61689b415667.gif
rp_tagger/static/__debug__/__1ed3bbe8c03f800b9946247b3f9b786c.png
rp_tagger/static/__debug__/__2da5558f29057d73ce7c3f9c47421fd7.jpg
rp_tagger/static/__debug__/__6a7a5e123af8472436ab6d9c34b79a49.jpg
rp_tagger/static/__debug__/__83b34cf54967dc5b4b86fcc6c2be7deb.png
rp_tagger/static/__debug__/__bb37cb0d4e32d3fae711734d2fc67da9.webm
rp_tagger/static/__debug__/__e52e29058facca1dd2d021757294b540.webm
rp_tagger/static/__debug__/__f20e54aa04d69b2892e58e724e6887bb.gif
rp_tagger/static/css/.base.css.un~
rp_tagger/static/css/base.css
rp_tagger/static/css/base.css~
rp_tagger/static/img/__nothing__.txt
rp_tagger/static/js/jquery-3.6.0.min.js
rp_tagger/static/js/js.cookie.min.js
rp_tagger/templates/.base.html.un~
rp_tagger/templates/.detail.html.un~
rp_tagger/templates/.index.html.un~
rp_tagger/templates/.list.html.un~
rp_tagger/templates/.test.html.un~
rp_tagger/templates/.tree.html.un~
rp_tagger/templates/base.html
rp_tagger/templates/base.html~
rp_tagger/templates/detail.html
rp_tagger/templates/detail.html~
rp_tagger/templates/index.html
rp_tagger/templates/index.html~
rp_tagger/templates/list.html
rp_tagger/templates/list.html~
rp_tagger/templates/tree.html
rp_tagger/templates/tree.html~
rp_tagger-1.1.0.data/scripts/rp_tagger
test/__init__.py
test/shell.py
test/ut.py
test/ft/__init__.py
test/ft/test_server.py
test/test_images/a/__0adaa6d28a61b9ab8f6d61689b415667.gif
test/test_images/a/g/__f20e54aa04d69b2892e58e724e6887bb.gif
test/test_images/b/__6a7a5e123af8472436ab6d9c34b79a49.jpg
test/test_images/g/__1ed3bbe8c03f800b9946247b3f9b786c.png
test/test_images/g/__2da5558f29057d73ce7c3f9c47421fd7.jpg
test/test_images/g/__e52e29058facca1dd2d021757294b540.webm
test/test_images/g/book/1631556613948.jpg
rp_tagger-1.1.0.dist-info/LICENSE
rp_tagger-1.1.0.dist-info/METADATA
rp_tagger-1.1.0.dist-info/WHEEL
rp_tagger-1.1.0.dist-info/top_level.txt
rp_tagger-1.1.0.dist-info/RECORD
