Metadata-Version: 2.1
Name: rp-tagger
Version: 1.1.0
Summary: Tool for organizing image folders.
Home-page: https://github.com/Moist-Cat/
Author: Moist-Cat
Author-email: moistanonpy@gmail.com
License: UNKNOWN
Platform: UNKNOWN
Classifier: Programming Language :: Python :: 3
Classifier: License :: OSI Approved :: MIT License
Classifier: Operating System :: POSIX :: Linux
Requires-Python: >=3.8
License-File: LICENSE
Requires-Dist: sqlalchemy (>=1.4.*)
Requires-Dist: flask (>=1.1.*)
